[{"date":"2019-10-10","dateString":"10/10","endTime":"16:33:08.033","endTimeString":"16:33","name":"「菲波那切提示器」类化","startTime":"16:05:08.033","startTimeString":"16:05"},{"date":"2019-10-10","dateString":"10/10","endTime":"17:30:02.426","endTimeString":"17:30","name":"完全实现菲波那切数列提示","startTime":"17:05:02.426","startTimeString":"17:05"},{"date":"2019-10-10","dateString":"10/10","endTime":"18:57:38.111","endTimeString":"18:57","name":"下载刘润商学院相关内容","startTime":"18:32:38.111","startTimeString":"18:32"},{"date":"2019-10-10","dateString":"10/10","endTime":"20:19:39.418","endTimeString":"20:19","name":"计划下周的任务(已完成)","startTime":"19:54:39.418","startTimeString":"19:54"},{"date":"2019-10-11","dateString":"10/11","endTime":"07:55:25.688","endTimeString":"07:55","name":"复习Anki英语","startTime":"07:30:25.688","startTimeString":"07:30"},{"date":"2019-10-11","dateString":"10/11","endTime":"08:27:18.802","endTimeString":"08:27","name":"1. 播放音乐问题的检测(未完) 2. 实现JSON存储配置(未完)","startTime":"08:02:18.802","startTimeString":"08:02"},{"date":"2019-10-11","dateString":"10/11","endTime":"09:02:48","endTimeString":"09:02","name":"成功的将配置文件改为在res目录下","startTime":"08:37:48","startTimeString":"08:37"},{"date":"2019-10-11","dateString":"10/11","endTime":"09:35:13.380","endTimeString":"09:35","name":"复习Anki英语","startTime":"09:10:13.380","startTimeString":"09:10"},{"date":"2019-10-11","dateString":"10/11","endTime":"10:49:36.777","endTimeString":"10:49","name":"实现Javazoom的Mp3播放(未完)","startTime":"10:24:36.777","startTimeString":"10:24"},{"date":"2019-10-11","dateString":"10/11","endTime":"11:50:36.777","endTimeString":"11:50","name":"实现Javazoom的Mp3播放（完成）","startTime":"10:25:36.777","startTimeString":"10:25"},{"date":"2019-10-11","dateString":"10/11","endTime":"13:47:15.662","endTimeString":"13:47","name":"实现properties的独立(进行中)","startTime":"13:22:15.662","startTimeString":"13:22"},{"date":"2019-10-11","dateString":"10/11","endTime":"14:18:45.301","endTimeString":"14:18","name":"1. 实现properties的独立(完成) 2. 实现Size的记忆(进行中)","startTime":"13:53:45.301","startTimeString":"13:53"},{"date":"2019-10-11","dateString":"10/11","endTime":"18:02:38.590","endTimeString":"18:02","name":"1. 实现size自动保存和载入 2. 学习进程方法(under way)","startTime":"17:37:38.590","startTimeString":"17:37"},{"date":"2019-10-12","dateString":"10/12","endTime":"07:55:38.947","endTimeString":"07:55","name":"1. Thread常用方法的理论学习(完成) 2. Exercise_1(完成)","startTime":"07:30:38.947","startTimeString":"07:30"},{"date":"2019-10-12","dateString":"10/12","endTime":"08:27:51.157","endTimeString":"08:27","name":"Exercise_2_穷举(under way) ","startTime":"08:02:51.157","startTimeString":"08:02"},{"date":"2019-10-12","dateString":"10/12","endTime":"09:20:14.274","endTimeString":"09:20","name":"复习英语Anki","startTime":"08:55:14.274","startTimeString":"08:55"},{"date":"2019-10-12","dateString":"10/12","endTime":"09:56:02.643","endTimeString":"09:56","name":"继续设计穷举程序","startTime":"09:31:02.643","startTimeString":"09:31"},{"date":"2019-10-12","dateString":"10/12","endTime":"11:00:02.643","endTimeString":"11:00","name":"学习线程同步","startTime":"10:31:02.643","startTimeString":"10:31"},{"date":"2019-10-12","dateString":"10/12","endTime":"11:27:12.748","endTimeString":"11:27","name":"继续学习「线程同步」","startTime":"11:02:12.748","startTimeString":"11:02"},{"date":"2019-10-12","dateString":"10/12","endTime":"12:07:04.327","endTimeString":"12:07","name":"1. 学习完成了「线程安全的类」和「死锁」2. 「交互」(进行中)","startTime":"11:42:04.327","startTimeString":"11:42"},{"date":"2019-10-12","dateString":"10/12","endTime":"13:59:05.736","endTimeString":"13:59","name":"Anki复习","startTime":"13:34:05.736","startTimeString":"13:34"},{"date":"2019-10-12","dateString":"10/12","endTime":"18:05:10.940","endTimeString":"18:05","name":"复习英语Anki","startTime":"17:40:10.940","startTimeString":"17:40"},{"date":"2019-10-13","dateString":"10/13","endTime":"08:16:16.995","endTimeString":"08:16","name":"Anki复习","startTime":"07:51:16.995","startTimeString":"07:51"},{"date":"2019-10-13","dateString":"10/13","endTime":"08:46:38.846","endTimeString":"08:46","name":"学习JavaFX tutorial CSS style","startTime":"08:21:38.846","startTimeString":"08:21"},{"date":"2019-10-13","dateString":"10/13","endTime":"09:38:24.619","endTimeString":"09:38","name":"考虑下一步的学习方向问题","startTime":"09:13:24.619","startTimeString":"09:13"},{"date":"2019-10-13","dateString":"10/13","endTime":"11:04:37.566","endTimeString":"11:04","name":"学习CSS introduction","startTime":"10:39:37.566","startTimeString":"10:39"},{"date":"2019-10-22","dateString":"10/22","endTime":"10:20","endTimeString":"10:20","name":"xxx","startTime":"09:55:12.684","startTimeString":"09:55"},{"date":"2019-10-23","dateString":"10/23","endTime":"10:14","endTimeString":"10:14","name":"","startTime":"09:49","startTimeString":"09:49"}]